dmpfold/__init__.py
dmpfold/network.py
dmpfold/predict.py
dmpfold/train.py
dmpfold/train_clust.lst
dmpfold/example/3FGX.pdb
dmpfold/example/PF10963.aln
dmpfold-2.0.data/scripts/dmpfold
dmpfold-2.0.dist-info/LICENSE
dmpfold-2.0.dist-info/METADATA
dmpfold-2.0.dist-info/WHEEL
dmpfold-2.0.dist-info/top_level.txt
dmpfold-2.0.dist-info/RECORD
