Metadata-Version: 2.1
Name: dmpfold
Version: 2.0
Summary: Protein structure prediction with the DMPfold2 method
Home-page: https://github.com/psipred/DMPfold2
Author: UCL Bioinformatics Group
Author-email: psipred@cs.ucl.ac.uk
License: UNKNOWN
Keywords: protein structure prediction deep learning alignment end-to-end
Platform: UNKNOWN
Classifier: Programming Language :: Python :: 3
Classifier: License :: OSI Approved :: GNU General Public License v3 (GPLv3)
Classifier: Topic :: Scientific/Engineering :: Bio-Informatics
License-File: LICENSE
Requires-Dist: numpy
